{"title":"SANTOS, Júlio Veríssimo da Silva","cargoss":["dep. fed. RJ 1895-1905 e 1924-1929","sen. RJ 1930."],"author":null,"content":"**SANTOS, Júlio Veríssimo da Silva**\n\n\\* dep. fed. RJ 1895-1905 e 1924-1929; sen. RJ 1930.\n\n*Júlio Veríssimo da Silva Santos* nasceu em Cantagalo (RJ) no dia 17 de\nsetembro de 1845.\n\nIngressou na Faculdade de Direito de São Paulo em 1865, mas teve de\ninterromper o curso por problemas de saúde, só podendo concluí-lo em\n1883, quando se formou bacharel. Durante o Império, militou no Partido\nConservador.\n\nJá na República, foi vereador e presidente da Câmara Municipal de\nCantagalo. Eleito deputado federal pelo 3^o^ distrito do estado do Rio\nde Janeiro na vaga aberta após a morte de Ferreira da Luz, tomou posse\nem 10 de junho de 1895 com mandato até dezembro de 1896. Reeleito para\nas três legislaturas subsequentes, permaneceu na Câmara dos Deputados\naté 31 de dezembro de 1905. Voltou então a presidir a Câmara Municipal\nde Cantagalo de 1905 a 1906, de 1910 a 1917, em 1923 (em caráter\nprovisório), e ainda em 1926, quando perdeu o mandato por decisão do\nTribunal da Relação do Estado, tendo sido substituído por Antônio da\nSilva Pinto. A essa altura, já havia sido eleito deputado federal e\ntomado assento na Câmara dos Deputados em 12 de agosto de 1924. Renovou\no mandato ao fim da legislatura, em 31 de dezembro de 1926, e permaneceu\nna Câmara até 31 de dezembro de 1929.\n\nEm 1930 foi eleito senador. Tomou posse em maio, mas teve o mandato\ninterrompido em 23 de outubro pela revolução que levou Getúlio Vargas ao\npoder e extinguiu os órgãos legislativos do país.\n\nIzabel Pimentel da Silva\n\n**FONTES:** ABRANCHES, J. *Governos* (v.1); CÂM. DEP. *Deputados\nbrasileiros*; CÂM. MUN. CANTAGALO. *Galeria de Ex-Presidentes.*\nDisponível em: \\<www.cmcantagalo.rj.gov.br/ex-presidentes.htm\\>. Acesso\nem: 12/1/2011; LEITE NETO, L. *Catálogo biográfico;* SENADO. *Dados*\n*biográficos dos senadores do Rio de Janeiro;* SENADO. Disponível em:\n\\<www.senado.gov.br\\>.\n","ref":"**FONTES:** ABRANCHES, J. *Governos* (v.1); CÂM. DEP. *Deputados\nbrasileiros*; CÂM. MUN. CANTAGALO. *Galeria de Ex-Presidentes.*\nDisponível em: \\<www.cmcantagalo.rj.gov.br/ex-presidentes.htm\\>. Acesso\nem: 12/1/2011; LEITE NETO, L. *Catálogo biográfico;* SENADO. *Dados*\n*biográficos dos senadores do Rio de Janeiro;* SENADO. Disponível em:\n\\<www.senado.gov.br\\>.\n","dic":"DHBPR"}