{"title":"CONTINENTINO, Múcio","cargoss":["dep. fed. MG 1930."],"author":"Luciana Pinheiro","content":"**CONTINENTINO, Múcio**\n\n\\*dep. fed. MG 1930.\n\n*Múcio de Campos Continentino* nasceu em Oliveira (MG) no dia 20 de\nabril de 1895, filho de João Pereira da Silva Continentino e de Amanda\nCampos Continentino.\n\nEm 1916 diplomou-se pela Faculdade Livre de Direito de Minas Gerais.\nRecém-formado, iniciou a carreira profissional como advogado e foi\npromotor de justiça em seu município natal.\n\nEm março de 1930 e foi eleito deputado federal por Minas Gerais na\nlegenda do Partido Republicano Mineiro (PRM). Assumindo sua cadeira na\nCâmara dos Deputados, no Rio de Janeiro, então Distrito Federal, em maio\ndo mesmo ano, teve o mandato interrompido em outubro seguinte com a\nvitória da revolução que levou Getúlio Vargas ao poder e extinguiu todos\nos órgãos legislativos do país.\n\nEm outubro de 1943, quando da publicação do *Manifesto dos Mineiros*,\nfoi um dos 92 signatários do documento que defendia o fim da ditadura do\nEstado Novo (1937-1945) e a redemocratização do país.\n\nFoi também advogado na cidade do Rio de Janeiro.\n\nFaleceu em São Paulo no dia 30 de agosto de 1944.\n\nPublicou *Da cláusula penal no direito brasileiro* (1926)*.*\n\nLuciana Pinheiro\n\n**FONTES:** CÂM. DEP. *Deputados brasileiros* (p.195); CPDOC. Disponível\nem: \\<http://cpdoc.fgv.br/\\>. Acesso em: 21/9/2010; MONTEIRO, N.\n*Dicionário* (v.1, p.189).\n","ref":"**FONTES:** CÂM. DEP. *Deputados brasileiros* (p.195); CPDOC. Disponível\nem: \\<http://cpdoc.fgv.br/\\>. Acesso em: 21/9/2010; MONTEIRO, N.\n*Dicionário* (v.1, p.189).\n","dic":"DHBPR"}