{"title":"ALMEIDA, Domingos Mariano Barcelosde","cargoss":["dep. fed. RJ 1921-1923."],"author":null,"content":"**ALMEIDA, Domingos Mariano Barcelosde**\n\n\\* dep. fed. RJ 1921-1923.\n\n*Domingos Mariano Barcelos de Almeida* elegeu-se deputadoestadual no Rio\nde Janeiro em dezembrode 1909 para a legislatura 1910-1912.Iniciou o\nmandato no ano seguinte naAssembleia Legislativa do Estado do Riode\nJaneiro (ALERJ) e integrou a Comissãode Justiça, Legislação e Instrução\nPública.Nas eleições de 15 de dezembro de1915, foi novamente eleito\ndeputado estadualpara a legislatura 1916-1918. Durante esseperíodo\nintegrou a Comissão de Fazenda,Orçamento e Força Pública.\n\nFoi prefeito da cidade de Piraí,localizada no vale do Paraíba\nfluminense.Durante sua gestão na prefeitura, fundouo Grupo Escolar\nMartins Teixeira, inauguradoem 1918 no prédio onde hoje selocaliza o\nforo da cidade. Ainda em1918, inaugurou o prédio da Delegaciade Polícia,\nconstruído por Bento GomesFranco, que ganhou a concorrência públicaem\n1917. O edifício integra hoje opatrimônio histórico e arquitetônico do\ncentrodo município de Piraí.\n\nDurante o governo de Raul deMorais Veiga, de 1918 a 1921, foiprimeiro\nvice-presidente do estado do Riode Janeiro, enquanto Mário de\nAzevedoQuintanilha e César Nascentes Tinoco ocupavamos postos de segundo\ne terceiro-vice-presidentes.No entanto, ainda durante o mesmo governo,a\nConstituição do estado foi alteradapela Lei n^o^ 1.670, de 15de novembro\nde 1920, que manteve apenasum cargo de vice-presidente, suprimindo\nosoutros dois.\n\nEm 1921 foi eleito deputado federalpelo estado do Rio de Janeiro.\nTomouposse em 3 de maio do mesmo anoe exerceu o mandato até 31 de\ndezembrode 1923.\n\nAo longo da vida, foi tambémsecretário geral do estado do Rio deJaneiro,\ntendo atuado juntamente com oMinistério da Viação e Obras Públicasnas\nobras de saneamento da Baixada Fluminense.\n\nIzabel Pimentel da Silva\n\n**FONTES:**ASSEMB. LEGISL. *Anai*s (1911);ASSEMB. LEGISL. *Anais*\n(1917); CÂM. DEP. *Deputados brasileiros*; COL. BRAS. GENEALOGIA.\nDisponívelem: \\<www.cbg.org.br/arquivos\\_genealogicos\\_r\\_02.html\\>;\nMELLO,M. *Parlamento*; Núcleo de Memória PolíticaCarioca e Fluminense.\nDisponível em: \\<www.alerj.rj.gov.br /memoria /historia\\>; Prefeitura\nMunicipalde Piraí. Disponível em:\n\\<www.pirai.rj.gov.br/web/page/historia9.asp\\>;SEBRAE-RJ. Caminhos do\nCafé. Roteiros eVestígios. Disponível em:\n\\<www.sebraerj.com.br/custom/pdf/cam/cafe/06\\_CaminhosDoCafe-RoteirosEVestigios.pdf\\>.\n","ref":"**FONTES:**ASSEMB. LEGISL. *Anai*s (1911);ASSEMB. LEGISL. *Anais*\n(1917); CÂM. DEP. *Deputados brasileiros*; COL. BRAS. GENEALOGIA.\nDisponívelem: \\<www.cbg.org.br/arquivos\\_genealogicos\\_r\\_02.html\\>;\nMELLO,M. *Parlamento*; Núcleo de Memória PolíticaCarioca e Fluminense.\nDisponível em: \\<www.alerj.rj.gov.br /memoria /historia\\>; Prefeitura\nMunicipalde Piraí. Disponível em:\n\\<www.pirai.rj.gov.br/web/page/historia9.asp\\>;SEBRAE-RJ. Caminhos do\nCafé. Roteiros eVestígios. Disponível em:\n\\<www.sebraerj.com.br/custom/pdf/cam/cafe/06\\_CaminhosDoCafe-RoteirosEVestigios.pdf\\>.\n","dic":"DHBPR"}